README.rst
setup.py
zoobus/__init__.py
zoobus.egg-info/PKG-INFO
zoobus.egg-info/SOURCES.txt
zoobus.egg-info/dependency_links.txt
zoobus.egg-info/not-zip-safe
zoobus.egg-info/requires.txt
zoobus.egg-info/top_level.txt
zoobus/log/__init__.py
zoobus/log/printlog.py
zoobus/system/__init__.py
zoobus/system/mutexrun.py
zoobus/system/systemsnapshoot.py
zoobus/thrift/__init__.py
zoobus/thrift/thrifthelper.py
zoobus/time/__init__.py
zoobus/time/i18n.py
zoobus/web/__init__.py
zoobus/web/htmlparse.py
zoobus/web/pagination.py