Metadata-Version: 1.1
Name: zoobus
Version: 0.1
Summary: Vincent Wen's Personal Common Packages
Home-page: https://github.com/vincentwyshan/ZooBus/archive/master.zip
Author: Vincent Wen
Author-email: vincent.wyshan@gmail.com
License: UNKNOWN
Platform: UNKNOWN
Classifier: License :: OSI Approved :: MIT License
Classifier: Programming Language :: Python
